{
  "status": "ok",
  "totalResults": 1180,
  "articles": [
    {
      "source": {
        "id": "wired",
        "name": "Wired"
      },
      "author": "Aarian Marshall",
      "title": "The Supreme Court's Tariff Ruling Won't Bring Car Prices Back to Earth",
      "description": "Despite Friday's SCOTUS ruling, many tariffs affecting the auto industry will remain. So will the other dynamics that have led to today's historically high car prices.",
      "url": "https://www.wired.com/story/the-supreme-courts-tariff-ruling-wont-bring-car-prices-back-to-earth/",
      "urlToImage": "https://media.wired.com/photos/6998dd8f557d4953e6dd73fe/191:100/w_1280,c_limit/New-Car-Prices-Gear--2255530950.jpg",
      "publishedAt": "2026-02-21T00:10:01Z",
      "content": "It has never been more expensive to buy a new car. The average transaction price last month for buyers in the United States was $48,576, up nearly a third from 2019, according to Edmunds. The afforda… [+2231 chars]"
    },
    {
      "source": {
        "id": "bbc-news",
        "name": "BBC News"
      },
      "author": null,
      "title": "Trump’s Tariffs: The Beginning of the End?",
      "description": "The Supreme Court has rejected US President Donald Trump’s global import taxes",
      "url": "https://www.bbc.co.uk/sounds/play/p0n2hg3q",
      "urlToImage": "https://ichef.bbci.co.uk/images/ic/1024x576/p0l7jnbt.jpg",
      "publishedAt": "2026-02-21T16:10:00Z",
      "content": "Available for over a year\r\nToday, Laura and Paddy are joined by Gary O'Donoghue, Chief North America correspondent to discuss the US Supreme Courts ruling to block President Donald Trumps global tari… [+1477 chars]"
    },
    {
      "source": {
        "id": null,
        "name": "BBC News"
      },
      "author": null,
      "title": "Trump ups tariffs day after Supreme Court ruling against him",
      "description": "The president will increase import taxes to 15% on most products coming into the US from Tuesday.",
      "url": "https://www.bbc.com/news/articles/cn8z48xwqn3o",
      "urlToImage": "https://ichef.bbci.co.uk/news/1024/branded_news/1a2d/live/537ff930-6139-11ee-b101-6f93d6dfbcc2.png",
      "publishedAt": "2026-02-21T16:13:35Z",
      "content": "US President Donald Trump has said that he will impose global tariffs of 15%, as he continued to rail against a Supreme Court ruling that struck down his previous import taxes."
    },
    {
      "source": {
        "id": null,
        "name": "BBC News"
      },
      "author": null,
      "title": "Trump administration fires Virginia prosecutor hours after judges appointed him",
      "description": "It is the second time this month that the Trump administration has abruptly fired a prosecutor who was appointed by judges.",
      "url": "https://www.bbc.com/news/articles/c4gqegwgp7wo",
      "urlToImage": "https://ichef.bbci.co.uk/news/1024/branded_news/a0f4/live/2b2ac470-0f41-11f1-9610-6bdfe89c38bb.jpg",
      "publishedAt": "2026-02-21T17:25:35Z",
      "content": "Days after Siebert's exit, Trump appointed Lindsey Halligan, a White House aide and the president's former personal attorney, to the position. Halligan quickly secured grand jury indictments against … [+31 chars]"
    },
    {
      "source": {
        "id": null,
        "name": "NPR"
      },
      "author": "Kristin Wright",
      "title": "Trump to raise global tariffs to 15%",
      "description": "President Trump previously said he would implement 10% global tariffs after the U.S. Supreme Court struck down his tariff policies.",
      "url": "https://www.npr.org/2026/02/21/nx-s1-5722111/trump-global-tariffs-15-percent",
      "urlToImage": "https://npr.brightspotcdn.com/dims3/default/strip/false/crop/6973x3922+0+0/resize/1400/quality/85/format/jpeg/?url=http%3A%2F%2Fnpr-brightspot.s3.amazonaws.com%2Fdd%2Fb1%2F1f494cb74151a2d2a6f29fa18f1e%2Fgettyimages-2262154068.jpg",
      "publishedAt": "2026-02-21T18:57:02Z",
      "content": "President Trump on Saturday said he plans to raise global tariffs from 10% to 15%.\r\n\"...I, as President of the United States of America, will be, effective immediately, raising the 10% Worldwide Tari… [+1685 chars]"
    },
    {
      "source": {
        "id": null,
        "name": "NPR"
      },
      "author": "Greg Myre",
      "title": "With U.S. forces in position, Trump mulls his options for Iran",
      "description": "President Trump says he hasn't decided whether to attack Iran. While he weighs his options, a military buildup over the past month means the U.S. now has an expansive presence in the region.",
      "url": "https://www.npr.org/2026/02/21/nx-s1-5720966/trump-iran",
      "urlToImage": "https://npr.brightspotcdn.com/dims3/default/strip/false/crop/5760x3240+0+300/resize/1400/quality/85/format/jpeg/?url=http%3A%2F%2Fnpr-brightspot.s3.amazonaws.com%2Ff3%2F66%2Fea05b9cb4be7aad488e4e3117cc6%2Fgettyimages-2261945019.jpg",
      "publishedAt": "2026-02-21T11:00:00Z",
      "content": "President Trump says he hasn't decided whether he'll launch a military strike on Iran. But he now has a wide range of options.\r\nAn American military buildup over the past month means the U.S. now has… [+5627 chars]"
    },
    {
      "source": {
        "id": null,
        "name": "NPR"
      },
      "author": "Windsor Johnston",
      "title": "Vietnam Veterans sue to block proposed 'Independence Arch' near Arlington National Cemetery",
      "description": "The lawsuit challenges President Trump's plans for \"Independence Arch,\" a 250-foot structure proposed for Memorial Circle.",
      "url": "https://www.npr.org/2026/02/21/nx-s1-5721786/vietnam-veterans-sue-trump-arch",
      "urlToImage": "https://npr.brightspotcdn.com/dims3/default/strip/false/crop/5777x3250+0+0/resize/1400/quality/85/format/jpeg/?url=http%3A%2F%2Fnpr-brightspot.s3.amazonaws.com%2F87%2F74%2F89bc5033437eafa3fc534e390f64%2Fap26034830892619.jpg",
      "publishedAt": "2026-02-21T19:27:56Z",
      "content": "A group of Vietnam War veterans and a retired architectural historian have filed a federal lawsuit seeking to block construction of a proposed monument near Arlington National Cemetery.\r\nThe lawsuit,… [+2534 chars]"
    },
    {
      "source": {
        "id": null,
        "name": "NPR"
      },
      "author": "The Associated Press",
      "title": "Court clears way for Louisiana law requiring Ten Commandments in classrooms to take effect",
      "description": "The 5th U.S. Circuit Court of Appeals has cleared the way for a Louisiana law requiring displays of the Ten Commandments in public classrooms to take effect.",
      "url": "https://www.npr.org/2026/02/21/nx-s1-5721734/court-louisiana-ten-commandments-in-classrooms-take-effect",
      "urlToImage": "https://npr.brightspotcdn.com/dims3/default/strip/false/crop/5535x3113+0+0/resize/1400/quality/85/format/jpeg/?url=http%3A%2F%2Fnpr-brightspot.s3.amazonaws.com%2F0b%2F0c%2F97565ca24208bee8f307deb1621c%2Fap26052024065343.jpg",
      "publishedAt": "2026-02-21T13:44:31Z",
      "content": "A U.S. appeals court has cleared the way for a Louisiana law requiring poster-sized displays of the Ten Commandments in public school classrooms to take effect.\r\nThe 5th U.S. Circuit Court of Appeals… [+4068 chars]"
    },
    {
      "source": {
        "id": null,
        "name": "Slashdot.org"
      },
      "author": "EditorDavid",
      "title": "America's Peace Corps Announces 'Tech Corps' Volunteers to Help Bring AI to Foreign Countries",
      "description": "Over 240,000 Americans volunteered for Peace Corps projects in 142 countries since the program began more than half a century ago. \n\nBut now the agency is launching a new initiative — called Tech Corps. \"It's the Peace Corps, but make it AI,\" explains Engadge…",
      "url": "https://yro.slashdot.org/story/26/02/21/2140216/americas-peace-corps-announces-tech-corps-volunteers-to-help-bring-ai-to-foreign-countries",
      "urlToImage": "https://a.fsdn.com/sd/topics/ai_64.png",
      "publishedAt": "2026-02-21T21:43:00Z",
      "content": "Over 240,000 Americans volunteered for Peace Corps projects in 142 countries since the program began more than half a century ago.But now the agency is launching a new initiative — called Tech Corps.… [+1346 chars]"
    },
    {
      "source": {
        "id": "business-insider",
        "name": "Business Insider"
      },
      "author": "Peter Gelling",
      "title": "Trump now says he will raise 'worldwide' tariff from 10% to 15%",
      "description": "President Donald Trump is not giving up on his tariff strategy.",
      "url": "https://www.businessinsider.com/trump-raise-global-tariff-supreme-court-2026-2",
      "urlToImage": "https://i.insider.com/6999e51defb52c8bd0de9e7d?width=1200&format=jpeg",
      "publishedAt": "2026-02-21T17:02:31Z",
      "content": "The House rejected a spending package that would end the partial government shutdown, despite pressure from President Donald Trump.AP Photo/Evan Vucci\r\n<ul><li>Trump says he will impose a 15% 'worldw… [+1974 chars]"
    },
    {
      "source": {
        "id": "business-insider",
        "name": "Business Insider"
      },
      "author": "Kelsey Vlamis",
      "title": "Democrats demand that Trump issue $1,700 tariff refunds to Americans after the Supreme Court ruling",
      "description": "Govs. Gavin Newsom and JB Pritzker demand Trump pay Americans $1,700 in tariff refunds after the Supreme Court ruling.",
      "url": "https://www.businessinsider.com/democrats-demand-trump-issue-1700-tariff-refunds-americans-supreme-court-2026-2",
      "urlToImage": "https://i.insider.com/6998f3d7efb52c8bd0de9cfc?width=1200&format=jpeg",
      "publishedAt": "2026-02-21T00:41:18Z",
      "content": "California Gov. Gavin Newsom called on Trump to pay back Americans for tariff costs.K.C. Alfred / The San Diego Union-Tribune via Getty Images\r\n<ul><li>Democrats are calling for Trump to issue Americ… [+3783 chars]"
    },
    {
      "source": {
        "id": "business-insider",
        "name": "Business Insider"
      },
      "author": "Sarah E. Needleman",
      "title": "Corporate America's toughest job? Being COO during the tariff whiplash",
      "description": "America's supply-chain bosses are experiencing a fresh bout of uncertainty after Friday's tariff ruling by the Supreme Court.",
      "url": "https://www.businessinsider.com/coo-job-is-especially-challenging-with-tariff-uncertainty-scotus-2026-2",
      "urlToImage": "https://i.insider.com/6998e680efb52c8bd0de9c8b?width=1200&format=jpeg",
      "publishedAt": "2026-02-21T10:39:01Z",
      "content": "Stephen B. Morton/AP\r\n<ul><li>The Supreme Court struck down much of Trump's tariffs, but Trump could try to impose levies in other ways.</li><li>COOs, who are responsible for overseeing where compani… [+5617 chars]"
    },
    {
      "source": {
        "id": null,
        "name": "Yahoo Entertainment"
      },
      "author": null,
      "title": "Murdoch Paper Flames Trump for ‘Worst Day of Presidency’",
      "description": null,
      "url": "https://consent.yahoo.com/v2/collectConsent?sessionId=1_cc-session_26ced8f5-61fb-4177-b91b-3e47f9a9c7a0",
      "urlToImage": null,
      "publishedAt": "2026-02-21T06:47:58Z",
      "content": "If you click 'Accept all', we and our partners, including 245 who are part of the IAB Transparency &amp; Consent Framework, will also store and / or access information on a device (in other words, us… [+1046 chars]"
    },
    {
      "source": {
        "id": null,
        "name": "Yahoo Entertainment"
      },
      "author": null,
      "title": "Trump Hit With Devastating Poll Numbers Amid Tariff Tantrum",
      "description": null,
      "url": "https://consent.yahoo.com/v2/collectConsent?sessionId=1_cc-session_e197e4de-2d02-4e9b-933e-00fbc07e5319",
      "urlToImage": null,
      "publishedAt": "2026-02-21T15:27:44Z",
      "content": "If you click 'Accept all', we and our partners, including 245 who are part of the IAB Transparency &amp; Consent Framework, will also store and / or access information on a device (in other words, us… [+1046 chars]"
    },
    {
      "source": {
        "id": null,
        "name": "Yahoo Entertainment"
      },
      "author": null,
      "title": "Trump Has A Favorite Tool For Keeping MAGA Followers Loyal. Experts Say It's Highly Effective.",
      "description": null,
      "url": "https://consent.yahoo.com/v2/collectConsent?sessionId=1_cc-session_e4fd9610-ae77-4562-b94a-122481f12170",
      "urlToImage": null,
      "publishedAt": "2026-02-21T17:46:02Z",
      "content": "If you click 'Accept all', we and our partners, including 245 who are part of the IAB Transparency &amp; Consent Framework, will also store and / or access information on a device (in other words, us… [+1046 chars]"
    },
    {
      "source": {
        "id": null,
        "name": "Yahoo Entertainment"
      },
      "author": null,
      "title": "Trump Wakes Up Blurting Praise For ‘My New Hero’ — And It’s About His Devastating Court Loss",
      "description": null,
      "url": "https://consent.yahoo.com/v2/collectConsent?sessionId=1_cc-session_4041fdcd-6bd0-458e-a0fa-581b0f94a1e0",
      "urlToImage": null,
      "publishedAt": "2026-02-21T15:59:25Z",
      "content": "If you click 'Accept all', we and our partners, including 245 who are part of the IAB Transparency &amp; Consent Framework, will also store and / or access information on a device (in other words, us… [+1046 chars]"
    },
    {
      "source": {
        "id": null,
        "name": "Yahoo Entertainment"
      },
      "author": null,
      "title": "US military airlifts small reactor as Trump pushes to quickly deploy nuclear power",
      "description": null,
      "url": "https://consent.yahoo.com/v2/collectConsent?sessionId=1_cc-session_51a64a01-d2c3-4adb-8542-e356bf633281",
      "urlToImage": null,
      "publishedAt": "2026-02-21T12:12:46Z",
      "content": "If you click 'Accept all', we and our partners, including 245 who are part of the IAB Transparency &amp; Consent Framework, will also store and / or access information on a device (in other words, us… [+1046 chars]"
    },
    {
      "source": {
        "id": null,
        "name": "Yahoo Entertainment"
      },
      "author": null,
      "title": "Woman Who ‘Credibly Accused’ Trump of Sex With a Minor Reportedly Had Her Records Removed From Epstein Files",
      "description": null,
      "url": "https://consent.yahoo.com/v2/collectConsent?sessionId=1_cc-session_aeb5afd0-c761-4ebb-9060-500898194c83",
      "urlToImage": null,
      "publishedAt": "2026-02-21T22:08:09Z",
      "content": "If you click 'Accept all', we and our partners, including 245 who are part of the IAB Transparency &amp; Consent Framework, will also store and / or access information on a device (in other words, us… [+1046 chars]"
    },
    {
      "source": {
        "id": null,
        "name": "Yahoo Entertainment"
      },
      "author": "CLAIRE GALOFARO",
      "title": "She was an orphan adopted from Iran by a US veteran. The Trump administration wants to deport her",
      "description": "A woman adopted as a toddler by an American war veteran, who he found in the 1970s in an Iranian orphanage and raised as a Christian, is being threatened...",
      "url": "https://www.yahoo.com/news/articles/she-orphan-adopted-iran-us-123031403.html",
      "urlToImage": "https://s.yimg.com/ny/api/res/1.2/rp0EZRlVv7GYno5lPd1i9Q--/YXBwaWQ9aGlnaGxhbmRlcjt3PTEyMDA7aD04MDA7Y2Y9d2VicA--/https://media.zenfs.com/en/ap.org/8ecb78938d3e89ab3cfeb11cf9c15fb7",
      "publishedAt": "2026-02-21T12:30:31Z",
      "content": "A woman adopted as a toddler by an American war veteran, who he found in the 1970s in an Iranian orphanage and raised as a Christian, is being threatened with deportation to Iran, a country notorious… [+8612 chars]"
    },
    {
      "source": {
        "id": null,
        "name": "Yahoo Entertainment"
      },
      "author": null,
      "title": "Huckabee Sanders on tariffs: Fastest way to get Trump to act is ‘tell him that he can’t’",
      "description": null,
      "url": "https://consent.yahoo.com/v2/collectConsent?sessionId=1_cc-session_c325c226-1226-4ac0-9805-d77055c6ea59",
      "urlToImage": null,
      "publishedAt": "2026-02-21T14:10:00Z",
      "content": "If you click 'Accept all', we and our partners, including 245 who are part of the IAB Transparency &amp; Consent Framework, will also store and / or access information on a device (in other words, us… [+1046 chars]"
    },
    {
      "source": {
        "id": null,
        "name": "Yahoo Entertainment"
      },
      "author": "Associated Press",
      "title": "Utah’s Supreme Court rejects appeal to overturn congressional map with Democratic-leaning district",
      "description": "Utah’s Supreme Court rejected on Friday an appeal by Republican lawmakers and left in place a congressional map that gives Democrats a high chance of picking...",
      "url": "https://www.yahoo.com/news/articles/utah-supreme-court-rejects-appeal-065435482.html",
      "urlToImage": "https://s.yimg.com/ny/api/res/1.2/mpKE9DdklH9tnE4s4DnW3Q--/YXBwaWQ9aGlnaGxhbmRlcjt3PTEyMDA7aD04MDA7Y2Y9d2VicA--/https://media.zenfs.com/en/ap.org/0495546e2d947b35fd1080a03b468198",
      "publishedAt": "2026-02-21T06:54:35Z",
      "content": "SALT LAKE CITY (AP) Utahs Supreme Court rejected on Friday an appeal by Republican lawmakers and left in place a congressional map that gives Democrats a high chance of picking up one of the states f… [+2551 chars]"
    },
    {
      "source": {
        "id": null,
        "name": "Abcnews.com"
      },
      "author": "ABC News",
      "title": "WATCH: Trump condemns SCOTUS justices, announces new global tariffs after major ruling",
      "description": "President Trump on Friday outlined a new plan to impose his global tariffs after the Supreme Court struck down most of the levies as illegal — a decision he lambasted as \"deeply disappointing.\"",
      "url": "https://abcnews.com/video/130358826/",
      "urlToImage": "https://i.abcnewsfe.com/a/44e4049f-833d-494e-a82b-fc31d604000d/260220_abc_soc_trump_tariffs_hpMain_9x16.jpg?w=992",
      "publishedAt": "2026-02-21T06:07:27Z",
      "content": "<ul><li>Trump blasts Supreme Court's decision to strike down most of his tariffs\r\n</li><li>Masked man on Nancy Guthrie's doorstep may have had accomplice, sheriff's office says\r\n</li><li>Looking back… [+4534 chars]"
    },
    {
      "source": {
        "id": null,
        "name": "Abcnews.com"
      },
      "author": "ABC News",
      "title": "WATCH: Combating social media in the 'brain rot' era",
      "description": "ABC News’ Will Ganss looks at new ways to curb our cellphone obsession and cut down on screen time.",
      "url": "https://abcnews.com/video/130362981/",
      "urlToImage": "https://i.abcnewsfe.com/a/44b3db41-dbb7-4561-96f4-333e53eb9d94/260221_gma_ganss_socialmedia2_hpMain_16x9.jpg?w=992",
      "publishedAt": "2026-02-21T15:09:21Z",
      "content": "<ul><li>Trump blasts Supreme Court's decision to strike down most of his tariffs\r\n</li><li>Masked man on Nancy Guthrie's doorstep may have had accomplice, sheriff's office says\r\n</li><li>Looking back… [+4534 chars]"
    },
    {
      "source": {
        "id": null,
        "name": "Abcnews.com"
      },
      "author": "ABC News",
      "title": "WATCH: Baby giraffe and ostrich face off in 'staring contest'",
      "description": "Rahisi, a young giraffe, engaged in a “staring contest” with an ostrich in a neighboring habitat at the Memphis Zoo.",
      "url": "https://abcnews.com/video/130368580/",
      "urlToImage": "https://i.abcnewsfe.com/a/4143ba75-61f9-44c3-8bf2-ce94b52e1e5d/260221_abc_social_zoo_stare_hpMain_9x16.jpg?w=992",
      "publishedAt": "2026-02-21T17:37:40Z",
      "content": "<ul><li>Winter storms head toward Northeast\r\n</li><li>US military moves into position for possible Iran strikes\r\n</li><li>Nancy Guthrie disappearance reaches 3-week mark\r\n</li><li>What Trump tariffs … [+4499 chars]"
    },
    {
      "source": {
        "id": null,
        "name": "Abcnews.com"
      },
      "author": "ABC News",
      "title": "WATCH: Reese's heir accuses Hershey of cutting corners",
      "description": "Brad Reese explains why he believes ingredient changes undermine his grandfather's original creation.",
      "url": "https://abcnews.com/video/130352588/",
      "urlToImage": "https://i.abcnewsfe.com/a/56ace30d-2e53-49a6-a686-821fb6b9f703/260220_abcnl_6p_candy_brad_reese2_hpMain_16x9.jpg?w=992",
      "publishedAt": "2026-02-21T00:29:01Z",
      "content": "<ul><li>Whats next for tariffs after the Supreme Court ruling?\r\n</li><li>Trump outlines new plan for tariffs Supreme Court decision\r\n</li><li>Legal implications of SCOTUS ruling on Trump tariffs\r\n</l… [+4295 chars]"
    },
    {
      "source": {
        "id": null,
        "name": "The New Yorker"
      },
      "author": "The New Yorker",
      "title": "The MAGA Agenda Is Sinking in Popularity. What Might Donald Trump Do?",
      "description": "On The Political Scene Podcast: What to expect at the State of the Union.",
      "url": "https://www.newyorker.com/podcast/political-scene/the-maga-agenda-is-sinking-in-popularity-what-might-donald-trump-do",
      "urlToImage": "https://media.newyorker.com/photos/65496ea9e960b0ea67668dc7/16:9/w_1280,c_limit/The%20Political%20Scene%20B%20Glasser%20Mayer%20Osnos%20From%20Washington.jpg",
      "publishedAt": "2026-02-21T04:59:00Z",
      "content": "Listen and subscribe:Apple | Spotify | Wherever You Listen\r\nSign upto receive our twice-weekly News &amp; Politics newsletter.\r\nThe Washington Roundtable discusses the upcoming State of the Union add… [+1083 chars]"
    },
    {
      "source": {
        "id": null,
        "name": "The New Yorker"
      },
      "author": "Ishaan Tharoor",
      "title": "Donald Trump’s Pantomime United Nations",
      "description": "The Board of Peace might be destined to fail, but it still threatens to undermine an international system in which the U.S. was once the linchpin. Ishaan Tharoor writes.",
      "url": "https://www.newyorker.com/news/the-lede/donald-trumps-pantomime-united-nations",
      "urlToImage": "https://media.newyorker.com/photos/6998ad0f243e066c18b05ae3/16:9/w_1280,c_limit/Tharoor_BoardofPeace_2026-02-19T171416Z_1519238211_RC23PJA064KN_RTRMADP_3_ISRAEL-PALESTINIANS-GAZA-TRUMP-BOARD.jpg",
      "publishedAt": "2026-02-21T19:23:14Z",
      "content": "The current membership of the board is a motley mix. It includes prominent countries already invested in bringing stability to GazaTurkey, Egypt, Jordan, the Gulf monarchies. The White House has also… [+4831 chars]"
    },
    {
      "source": {
        "id": null,
        "name": "The Atlantic"
      },
      "author": "The Editors",
      "title": "What to Expect from Trump’s State of the Union Address",
      "description": "Panelists join to preview the president’s upcoming remarks.&nbsp;&nbsp;",
      "url": "https://www.theatlantic.com/national/2026/02/trump-state-of-the-union-washington-week/686100/",
      "urlToImage": "https://cdn.theatlantic.com/thumbor/xNyP3FL2v90iQzHsUsFTItuj42g=/3x98:2606x1454/1200x625/media/img/mt/2026/02/Screenshot_2026_02_21_at_9.44.33AM/original.png",
      "publishedAt": "2026-02-21T18:44:32Z",
      "content": "Editor’s Note: Washington Week With The Atlantic is a partnership between NewsHour Productions, WETA, and The Atlantic airing every Friday on PBS stations nationwide. Check your local listings, watch… [+1047 chars]"
    },
    {
      "source": {
        "id": null,
        "name": "BBC News"
      },
      "author": null,
      "title": "Trump lashes out at Supreme Court justices over tariffs ruling",
      "description": "The six justices who voted against the tariffs, dealing a major blow to his signature economic policy, should be \"absolutely ashamed\", Trump said.",
      "url": "https://www.bbc.com/news/articles/cd9g0e7zd8wo",
      "urlToImage": "https://ichef.bbci.co.uk/news/1024/branded_news/e655/live/f8089780-0eb8-11f1-b048-c9424b2cf5fd.jpg",
      "publishedAt": "2026-02-21T00:49:09Z",
      "content": "At the same time, Trump heaped praise on the three members of the court, Justices Clarence Thomas, Samuel Alito, and Brett Kavanaugh, who voted to keep his tariffs authority intact."
    },
    {
      "source": {
        "id": null,
        "name": "Ritholtz.com"
      },
      "author": "Barry Ritholtz",
      "title": "10 Weekend Reads",
      "description": "The weekend is here! Pour yourself a mug of Danish Blend coffee, grab a seat outside, and get ready for our longer-form weekend reads: • This Entertainment Lawyer to the Stars Shares His Best Negotiating Secret: Allen Grubman on why you should always overtip …",
      "url": "https://ritholtz.com/2026/02/10-weekend-reads-79/",
      "urlToImage": "https://ritholtz.com/wp-content/uploads/2029/12/onlinespending.png",
      "publishedAt": "2026-02-21T11:30:08Z",
      "content": "The weekend is here! Pour yourself a mug of Danish Blend coffee, grab a seat outside, and get ready for our longer-form weekend reads:This Entertainment Lawyer to the Stars Shares His Best Negotiatin… [+5205 chars]"
    },
    {
      "source": {
        "id": null,
        "name": "Marginalrevolution.com"
      },
      "author": "Alex Tabarrok",
      "title": "Why the “Lesser Included Action” Argument for IEEPA Tariffs Fails",
      "description": "The Supreme Court yesterday struck down Trump’s IEEPA tariffs, holding that the statute’s authorization to “regulate… importation” doesn’t include the power to impose tariffs. The majority’s strongest argument is simple: every time Congress actually delegates…",
      "url": "https://marginalrevolution.com/marginalrevolution/2026/02/why-the-lesser-included-action-argument-for-ieepa-tariffs-fails.html",
      "urlToImage": "https://marginalrevolution.com/wp-content/uploads/2016/10/MR-logo-thumbnail.png",
      "publishedAt": "2026-02-21T12:21:23Z",
      "content": "The Supreme Court yesterday struck down Trump’s IEEPA tariffs, holding that the statute’s authorization to “regulate… importation” doesn’t include the power to impose tariffs. The majority’s stronges… [+3963 chars]"
    },
    {
      "source": {
        "id": null,
        "name": "PetaPixel"
      },
      "author": "Jeremy Gray",
      "title": "The Tariff Situation Isn’t Getting Better for Photographers After All",
      "description": "Yesterday, the U.S. Supreme Court struck down President Trump's global tariffs he instituted last year based on the 1977 International Emergency Economic Powers Act (IEEPA). Hours later, the president announced new 10% global tariffs against most imports unde…",
      "url": "https://petapixel.com/2026/02/21/the-tariff-situation-isnt-getting-better-for-photographers-after-all/",
      "urlToImage": "https://petapixel.com/assets/uploads/2026/02/tariffs-15pct-opinion-featured.jpg",
      "publishedAt": "2026-02-21T18:47:37Z",
      "content": "Yesterday, the U.S. Supreme Court struck down President Trump’s global tariffs he instituted last year based on the 1977 International Emergency Economic Powers Act (IEEPA). Hours later, the presiden… [+4313 chars]"
    },
    {
      "source": {
        "id": null,
        "name": "Techdirt"
      },
      "author": "Timothy Geigner",
      "title": "Court Orders Slavery Exhibit At George Washington’s House Restored After Trump Admin Pulled It Down",
      "description": "The Trump administration’s project for erasing the parts of American history they find inconvenient continues unabated. But that doesn’t mean it doesn’t hit the occasional roadblock. In January, the administration removed portions of an exhibit at the former …",
      "url": "https://www.techdirt.com/2026/02/20/court-orders-slavery-exhibit-at-george-washingtons-house-restored-after-trump-admin-pulled-it-down/",
      "urlToImage": "https://www.techdirt.com/wp-content/themes/techdirt/assets/images/td-rect-logo-white.png",
      "publishedAt": "2026-02-21T03:39:00Z",
      "content": "from the history-in-the-unmaking dept\r\nThe Trump administration’s project for erasing the parts of American history they find inconvenient continues unabated. But that doesn’t mean it doesn’t hit the… [+5014 chars]"
    },
    {
      "source": {
        "id": null,
        "name": "TMZ"
      },
      "author": "TMZ Staff",
      "title": "Nancy Guthrie Abduction: Timeline of Events",
      "description": "Nancy left in an Uber at 5:32 PM to have dinner at her daughter Annie's house in Tucson, Arizona. At 9:48 PM, Nancy's son-in-law, Tommaso Cioni, dropped her back off at her home. Tommaso, Annie's husband, reportedly waited 2 minutes for Nancy to…",
      "url": "https://www.tmz.com/2026/02/21/nancy-guthrie-timeline/",
      "urlToImage": "https://imagez.tmz.com/image/54/16by9/2026/02/18/5406129a3ba048bcb5ca03b61c64a9d2_xl.jpg",
      "publishedAt": "2026-02-21T14:00:23Z",
      "content": "Nancy left in an Uber at 5:32 PM to have dinner at her daughter Annie's house in Tucson, Arizona.\r\nAt 9:48 PM, Nancy's son-in-law, Tommaso Cioni, dropped her back off at her home. Tommaso, Annie's hu… [+5983 chars]"
    },
    {
      "source": {
        "id": "al-jazeera-english",
        "name": "Al Jazeera English"
      },
      "author": "Maziar Motamedi",
      "title": "Iran demands ‘evidence’ as Trump, UN experts highlight protest killings",
      "description": "UN experts said discrepancy between official figures and grassroots estimates is compounding the anguish of families.",
      "url": "https://www.aljazeera.com/news/2026/2/21/iran-demands-evidence-as-trump-un-experts-highlight-protest-killings",
      "urlToImage": "https://www.aljazeera.com/wp-content/uploads/2026/02/afp_69998f348282-1771671348.jpg?resize=1920%2C1440",
      "publishedAt": "2026-02-21T11:54:58Z",
      "content": "Tehran, Iran The Iranian government has again blamed terrorists for the killings of thousands during last months nationwide protests after United States President Donald Trump and human rights expert… [+5204 chars]"
    },
    {
      "source": {
        "id": "al-jazeera-english",
        "name": "Al Jazeera English"
      },
      "author": "Lyndal Rowlands",
      "title": "Trump, JD Vance vilify ‘lawless’ Supreme Court justices over tariff ruling",
      "description": "President Trump calls Supreme Court justices an 'embarrassment to their families' in 45-minute address to media.",
      "url": "https://www.aljazeera.com/news/2026/2/21/trump-jd-vance-vilify-lawless-supreme-court-justices-over-tariff-ruling",
      "urlToImage": "https://www.aljazeera.com/wp-content/uploads/2025/06/13141267-1750575204.jpg?resize=1920%2C1440",
      "publishedAt": "2026-02-21T02:46:25Z",
      "content": "United States President Donald Trump and his vice president, JD Vance, have launched personal attacks on the justices of the US Supreme Court and their families, after the countrys top court struck d… [+2016 chars]"
    },
    {
      "source": {
        "id": "al-jazeera-english",
        "name": "Al Jazeera English"
      },
      "author": "Lyndal Rowlands",
      "title": "Trump to make three-day visit to China next month, White House says",
      "description": "Three-day trip, at Beijing's invitation, comes more than eight years after Trump's first visit to China.",
      "url": "https://www.aljazeera.com/news/2026/2/21/trump-to-make-three-day-visit-to-china-next-month-white-house-says",
      "urlToImage": "https://www.aljazeera.com/wp-content/uploads/2026/02/AP25303108240056-1771644909.jpg?resize=1200%2C675",
      "publishedAt": "2026-02-21T07:18:23Z",
      "content": "Donald Trump will travel to China from March 31 to April 2, the White House has said, in what will be the first official visit to Beijing by a United States president since Trumps last trip there in … [+2162 chars]"
    },
    {
      "source": {
        "id": "al-jazeera-english",
        "name": "Al Jazeera English"
      },
      "author": "Lyndal Rowlands",
      "title": "Brazil’s Lula says Maduro should face trial in Venezuela, not US",
      "description": "Brazil's President Lula says fate of Venezuelan president should be determined by the 'people of Venezuela'.",
      "url": "https://www.aljazeera.com/news/2026/2/21/brazils-lula-says-maduro-should-face-trial-in-venezuela-not-us",
      "urlToImage": "https://www.aljazeera.com/wp-content/uploads/2026/02/2023-05-29T195024Z_307901182_RC2H81A3XA6J_RTRMADP_3_BRAZIL-SUMMIT-1771646841_150545-1771647008.jpg?resize=1200%2C630&quality=80",
      "publishedAt": "2026-02-21T04:22:42Z",
      "content": "Brazilian President Luiz Inacio Lula da Silva has said that Venezuelan President Nicolas Maduro should face trial, but that it should take place in a Venezuelan court, rather than in the United State… [+1857 chars]"
    },
    {
      "source": {
        "id": "al-jazeera-english",
        "name": "Al Jazeera English"
      },
      "author": "Al Jazeera Staff",
      "title": "World reacts as US top court limits Trump’s tariff powers",
      "description": "Some countries welcome the ruling, while others review trade deals and economic effect.",
      "url": "https://www.aljazeera.com/news/2026/2/21/trump-tariff-reactions",
      "urlToImage": "https://www.aljazeera.com/wp-content/uploads/2026/02/afp_69996a260525-1771661862.jpg?resize=1920%2C1440",
      "publishedAt": "2026-02-21T09:40:50Z",
      "content": "President Donald Trump has imposed a new 10 percent worldwide tariff after the United States Supreme Court struck down his previous trade measures, triggering immediate concern and responses from gov… [+8252 chars]"
    },
    {
      "source": {
        "id": "al-jazeera-english",
        "name": "Al Jazeera English"
      },
      "author": "Al Jazeera",
      "title": "Venezuela grants amnesty to 379 political prisoners",
      "description": "The move is in line with a new law, giving hope to throngs of others imprisoned over alleged plots to oust the government.",
      "url": "https://www.aljazeera.com/news/2026/2/21/venezuela-grants-amnesty-to-379-political-prisoners",
      "urlToImage": "https://www.aljazeera.com/wp-content/uploads/2026/01/AFP__20260131__94MV49Z__v1__HighRes__VenezuelaUsConflictCrisis-1-1769837471.jpg?resize=1920%2C1440",
      "publishedAt": "2026-02-21T09:51:57Z",
      "content": "Venezuelan authorities have granted amnesty to 379 political prisoners, according to a lawmaker, after a new law was enacted by interim authorities following the United States abduction of President … [+2673 chars]"
    },
    {
      "source": {
        "id": "al-jazeera-english",
        "name": "Al Jazeera English"
      },
      "author": "Al Jazeera Staff",
      "title": "US military says it attacked vessel in Pacific Ocean, killing three people",
      "description": "US military's Southern Command (SOUTHCOM) claimed the vessel was involved in drug trafficking, without providing proof.",
      "url": "https://www.aljazeera.com/news/2026/2/21/us-military-says-it-attacked-vessel-in-pacific-ocean-killing-three-people",
      "urlToImage": "https://www.aljazeera.com/wp-content/uploads/2025/01/breaking-news%402x-1738224674.webp?resize=1200%2C675",
      "publishedAt": "2026-02-21T01:04:15Z",
      "content": "The US military said it attacked a boat in the eastern Pacific, killing three people, in the latest strike on a vessel in international waters that Washington alleges was involved in drug trafficking… [+948 chars]"
    },
    {
      "source": {
        "id": "al-jazeera-english",
        "name": "Al Jazeera English"
      },
      "author": "Al Jazeera",
      "title": "Israeli army kills 2 Palestinians in strikes on Gaza during Ramadan",
      "description": "Latest Israeli attacks bring total death toll in Gaza since October 'ceasefire' to 614.",
      "url": "https://www.aljazeera.com/news/2026/2/21/israeli-military-kills-two-in-early-ramadan-strikes-in-gaza",
      "urlToImage": "https://www.aljazeera.com/wp-content/uploads/2026/02/AFP__20260221__98G79VP__v1__HighRes__PalestinianGazaIsraelConflict-1771691135.jpg?resize=1920%2C1440",
      "publishedAt": "2026-02-21T17:27:11Z",
      "content": "Israeli air strikes killed at least two Palestinians in Gaza on the third day of Ramadan in the latest breach of the truce deal signed with Hamas more than four months ago.\r\nThe attacks on Saturday o… [+2971 chars]"
    },
    {
      "source": {
        "id": "al-jazeera-english",
        "name": "Al Jazeera English"
      },
      "author": "David D. Lee",
      "title": "Gunmen on motorcycles kill at least 50 in northwest Nigeria: Report",
      "description": "Nigerian lawmaker reports ‘at least 50 people dead’ after attack as list of missing is still being compiled.",
      "url": "https://www.aljazeera.com/news/2026/2/21/gunmen-on-motorcycles-kill-at-least-50-in-northwest-nigeria-report",
      "urlToImage": "https://www.aljazeera.com/wp-content/uploads/2026/02/reuters_69899e12-1770626578.jpg?resize=1200%2C630",
      "publishedAt": "2026-02-21T03:38:23Z",
      "content": "Gunmen killed at least 50 people and abducted women and children in an overnight assault on a village in northwestern Nigerias Zamfara State, authorities and residents said.\r\nThe attack started late … [+2279 chars]"
    },
    {
      "source": {
        "id": "al-jazeera-english",
        "name": "Al Jazeera English"
      },
      "author": "Al Jazeera Staff",
      "title": "‘Absurd and provocative’: Huckabee faces firestorm for Israel border stance",
      "description": "Egypt, Jordan, Saudi Arabia denounce US ambassador's remarks suggesting Israel has right to much of the Middle East.",
      "url": "https://www.aljazeera.com/news/2026/2/21/absurd-and-provocative-huckabee-faces-firestorm-for-israel-border-stance",
      "urlToImage": "https://www.aljazeera.com/wp-content/uploads/2026/02/AFP__20250406__2206862767__v4__HighRes__SenateForeignRelationsCommitteeHoldsNominati-1771704111.jpg?resize=1920%2C1440",
      "publishedAt": "2026-02-21T21:31:19Z",
      "content": "United States Ambassador to Israel Mike Huckabee has triggered an avalanche of criticism from Arab and Muslim countries after suggesting Israel has a right to expand its territory across a large swat… [+3033 chars]"
    },
    {
      "source": {
        "id": null,
        "name": "CNBC"
      },
      "author": "Sarah Min",
      "title": "THE DON PUTS 15% TARIFF ON PLANET EARTH",
      "description": "THE DON PUTS 15% TARIFF ON PLANET EARTH\r\n\n \n \n \n (Main headline, 1st story, link)\r\n\n \r\n\n \r\n\n \n Related stories:'I CAN DO ANYTHING I WANT'\r\nWARNS ENEMIES HAVE INFILTRATED SUPREME COURT\r\n1063 DAYS LEFT IN OFFICE\r\n\n \r\n\n \n \n Drudge Report Feed needs your support!…",
      "url": "https://www.cnbc.com/2026/02/21/trump-tariffs.html",
      "urlToImage": "https://image.cnbcfm.com/api/v1/image/108268051-1771613719570-gettyimages-2262692728-kd1_2489_g870wvws.jpeg?v=1771613759&w=1920&h=1080",
      "publishedAt": "2026-02-21T16:34:36Z",
      "content": "President Donald Trump on Saturday said he would increase global tariffs to 15% from 10%, one day after the Supreme Court struck down his \"reciprocal\" tariffs. \r\nThe new tariffs will be \"effective im… [+1461 chars]"
    },
    {
      "source": {
        "id": null,
        "name": "Daily Beast"
      },
      "author": "David Rothkopf",
      "title": "ROTHKOPF: Trump's Tantrum Just the Beginning...",
      "description": "ROTHKOPF: Trump's Tantrum Just the Beginning...\r\n\n \n \n \n (Second column, 2nd story, link)\r\n\n \r\n\n \r\n\n \n Related stories:Next He Will Go After Elections...",
      "url": "https://www.thedailybeast.com/the-world-is-learning-to-say-no-to-donald-trump/",
      "urlToImage": "https://www.thedailybeast.com/resizer/v2/SPP7AE2JLJERTLU3FBA5J457FE.jpg?smart=true&auth=33e29d314cbcc4e76a6725fbd36bb60bf3ad2e0287724ff89b63fce004d48337&width=1200&height=630",
      "publishedAt": "2026-02-21T15:31:37Z",
      "content": "Donald Trump on Friday attacked the Supreme Court majority that ruled against him in a landmark decision on tariffs with a venom and ferocity he has never directed against Americas foreign enemies. H… [+7460 chars]"
    },
    {
      "source": {
        "id": null,
        "name": "Semafor.com"
      },
      "author": "Liz Hoffman",
      "title": "More drama from The Billionaires...",
      "description": "More drama from The Billionaires...\r\n\n \n \n \n (First column, 3rd story, link)\r\n\n \r\n\n \r\n\n \n Related stories:Firm of Lutnick family DENIES report it stands to make fortune from tariff ruling...\r\n\n \r\n\n \n \n Drudge Report Feed needs your support!   Become a Patron",
      "url": "https://www.semafor.com/article/02/20/2026/cantor-fitzgerald-howard-lutnicks-old-firm-did-not-profit-from-supreme-court-tariff-ruling",
      "urlToImage": "https://img.semafor.com/0c4023f2c822338545bc36b52b300b84d4cb1db0-5373x3582.jpg?rect=0,381,5373,2821&w=1200&h=630&q=75&auto=format",
      "publishedAt": "2026-02-21T11:55:36Z",
      "content": "Cantor Fitzgerald is rejecting claims that it sold a product that would pay off if the Supreme Court ruled, as it did Friday, against tariffs imposed by the Trump administration, where Cantors founde… [+1641 chars]"
    },
    {
      "source": {
        "id": "associated-press",
        "name": "Associated Press"
      },
      "author": "Sam Mednick, Samy Magdy",
      "title": "US ambassador causes uproar claiming Israel has right to much of Middle East...",
      "description": "Arab and Muslim countries are sharply condemning comments by the U.S. ambassador to Israel, who said in an interview that Israel had a right to much of the Middle East. Ambassador Mike Huckabee spoke in an interview with conservative commentator Tucker Carlso…",
      "url": "https://apnews.com/article/israel-ambassador-huckabee-middle-east-arab-muslim-e88a235c48bfb904f0ee7f8a72edf250",
      "urlToImage": "https://dims.apnews.com/dims4/default/fce6c47/2147483647/strip/true/crop/5616x3742+0+1/resize/980x653!/quality/90/?url=https%3A%2F%2Fassets.apnews.com%2F86%2F05%2Ff4ba1c9a2bbd0f76a129c80d701e%2F72e8844c89fd494c84fd0020a9684c92",
      "publishedAt": "2026-02-21T16:34:36Z",
      "content": "TEL AVIV, Israel (AP) Arab and Muslim nations on Saturday sharply condemned comments by the U.S. ambassador to Israel, Mike Huckabee, who said Israel has a right to much of the Middle East.\r\nHuckabee… [+3697 chars]"
    },
    {
      "source": {
        "id": null,
        "name": "Deadline"
      },
      "author": "Ted Johnson",
      "title": "Donald Trump Calls On Netflix To Fire Board Member Susan Rice Or “Pay The Consequences”",
      "description": "Donald Trump called on Netflix to fire one of its board members, Susan Rice, the former U.S. ambassador to the United Nations and national security adviser, following comments she made about accountability when Democrats return to power. Trump posted on Truth…",
      "url": "http://deadline.com/2026/02/trump-netflix-susan-rice-warner-bros-1236731945/",
      "urlToImage": "https://deadline.com/wp-content/uploads/2025/12/Ted-Sarandos-and-Donald-Trump.jpg?w=1024",
      "publishedAt": "2026-02-21T23:52:14Z",
      "content": "Donald Trump called on Netflix to fire one of its board members, Susan Rice, the former U.S. ambassador to the United Nations and national security adviser, following comments she made about accounta… [+3764 chars]"
    },
    {
      "source": {
        "id": null,
        "name": "Deadline"
      },
      "author": "Glenn Garner",
      "title": "‘Real Time’: Bill Maher Responds To Trump’s Truth Social Rant, Jokes POTUS Expected Him To “Put Out” After Dinner",
      "description": "Following a public Valentine’s Day breakup with his former pal Donald Trump, Bill Maher has shared his reaction to the president’s recent rant. On Friday’s episode of Real Time, the comedian joked he knows “how women feel now” after a guy buys them dinner and…",
      "url": "http://deadline.com/2026/02/real-time-bill-maher-responds-trump-truth-social-rant-1236731736/",
      "urlToImage": "https://deadline.com/wp-content/uploads/2026/02/Bill-Maher-Donald-Trump-2-shot.jpg?w=1024",
      "publishedAt": "2026-02-21T17:24:57Z",
      "content": "Following a public Valentine’s Day breakup with his former pal Donald Trump, Bill Maher has shared his reaction to the president’s recent rant.\r\nOn Friday’s episode of Real Time, the comedian joked h… [+1532 chars]"
    },
    {
      "source": {
        "id": null,
        "name": "Salon"
      },
      "author": "Russell Payne",
      "title": "Trump admin seeks to strike Epstein connections from record",
      "description": "The Trump admin employs an extreme stalling tactic in suit concerning potential Epstein-related Trump interviews",
      "url": "https://www.salon.com/2026/02/21/trump-admin-seeks-to-strike-epstein-connections-from-record/",
      "urlToImage": "https://www.salon.com/app/uploads/2025/11/epstein-files-handoff.jpg",
      "publishedAt": "2026-02-21T11:30:00Z",
      "content": "The Trump administration is using an irregular legal tactic in an attempt to suppress court info, including regarding the presidents relationship with convicted sex offender Jeffrey Epstein. In multi… [+5467 chars]"
    },
    {
      "source": {
        "id": null,
        "name": "Salon"
      },
      "author": "CK Smith",
      "title": "Trump escalates tariffs despite Supreme Court loss",
      "description": "The Supreme Court said “no,” so Trump found another way to impose 15% duties, showcasing his political agenda",
      "url": "https://www.salon.com/2026/02/21/trump-escalates-tariffs-despite-supreme-court-loss/",
      "urlToImage": "https://www.salon.com/app/uploads/2026/02/GettyImages-2262729717.jpg",
      "publishedAt": "2026-02-21T19:41:37Z",
      "content": "After the Donald Trump administration suffered a major legal rebuke this week from the Supreme Court of the United States which struck down the legal basis for his sweeping global tariff program Trum… [+1834 chars]"
    },
    {
      "source": {
        "id": null,
        "name": "Salon"
      },
      "author": "Chauncey DeVega",
      "title": "Even Trump’s forgotten Americans are turning against him",
      "description": "Low-information and poor white voters are turning against the president. Can Democrats win them back?",
      "url": "https://www.salon.com/2026/02/21/even-trumps-forgotten-americans-are-turning-against-him/",
      "urlToImage": "https://www.salon.com/app/uploads/2025/10/Donald-Trump-2238138813.jpg",
      "publishedAt": "2026-02-21T11:45:56Z",
      "content": "The mainstream media and political class were blindsided by Donald Trumps victory in the 2024 presidential election. They were so fixated on stereotypes and caricatures about the MAGA movement and Tr… [+7540 chars]"
    },
    {
      "source": {
        "id": null,
        "name": "Salon"
      },
      "author": "Austin Sarat",
      "title": "Supreme Court’s tariffs ruling reveals two political orders",
      "description": "Like the country itself, the justices are divided between democracy and authoritarianism",
      "url": "https://www.salon.com/2026/02/21/supreme-courts-tariffs-ruling-reveals-two-political-orders/",
      "urlToImage": "https://www.salon.com/app/uploads/2024/05/donald_trump_scotus_2151947511_2079442545.jpg",
      "publishedAt": "2026-02-21T14:00:11Z",
      "content": "The American people have grown used to reading about Supreme Court cases decided by a 6-3 vote. In almost all of those rulings, the courts six conservatives are arrayed on one side, with its three li… [+6901 chars]"
    },
    {
      "source": {
        "id": null,
        "name": "Salon"
      },
      "author": "Eleanor Klibanoff, Alejandro Serrano",
      "title": "Tony Gonzales accuses dead staffer’s husband of trying to blackmail him amid affair scandal",
      "description": "The Texas Republican shared an email requesting a settlement of up to $300,000 in exchange for an NDA.",
      "url": "https://www.salon.com/2026/02/21/texas-republican-tony-gonzales-accuses-dead-staffers-husband-of-trying-to-blackmail-him-amid-affai-partner/",
      "urlToImage": "https://www.salon.com/app/uploads/2024/04/tony-gonzales-1935921316.jpg",
      "publishedAt": "2026-02-21T11:00:07Z",
      "content": "Republican U.S. Rep. Tony Gonzales of San Antonio on Thursday claimed he was being blackmailed by the husband of a former staffer who died by suicide. Earlier this week, the San Antonio Express-News … [+5955 chars]"
    },
    {
      "source": {
        "id": null,
        "name": "The Indian Express"
      },
      "author": "Arav Shah",
      "title": "Why India’s decades-old friendship with France persists despite pressures from Trump 2.0",
      "description": "Even as US President Donald Trump continues to shake down the post-World War II established global order, France has managed to remain important for Indian interests",
      "url": "https://indianexpress.com/article/explained/explained-global/india-france-friendship-trump-us-10543237/",
      "urlToImage": "https://images.indianexpress.com/2026/02/ex-Ind-Fra_expl-geop.jpg",
      "publishedAt": "2026-02-21T02:52:54Z",
      "content": "On Tuesday (February 17), Prime Minister Narendra Modi and French President Emmanuel Macron virtually inaugurated the Final Assembly Line for Airbuss H125 helicopters in Vemagal, Karnataka. Developed… [+4030 chars]"
    },
    {
      "source": {
        "id": null,
        "name": "The Indian Express"
      },
      "author": "Rishika Singh",
      "title": "As US forces near Iran, what we know so far about the prospects of an attack",
      "description": "What is the scale of the military build-up right now? What has Donald Trump said, and how has Iran responded? What could happen next? We explain.",
      "url": "https://indianexpress.com/article/explained/explained-global/as-us-forces-near-iran-what-we-know-so-far-about-the-prospects-of-an-attack-10543351/",
      "urlToImage": "https://images.indianexpress.com/2026/02/US_5caedb1.jpg",
      "publishedAt": "2026-02-21T01:00:40Z",
      "content": "Less than a year after the United States and Israeli military forces attacked Iranian nuclear facilities in June 2025, the odds of another strike or even a bigger attack on Iran are growing.The BBC h… [+6716 chars]"
    },
    {
      "source": {
        "id": null,
        "name": "The Indian Express"
      },
      "author": "Express Web Desk",
      "title": "‘He will surrender again’: Rahul Gandhi’s jibe at PM Modi after Trump cuts global tariffs to 10%",
      "description": "Gandhi has been criticising the Centre over the interim India-US trade agreement framework, with his Budget speech in the Lok Sabha revolving around the specifics, or the lack of it, of the deal.",
      "url": "https://indianexpress.com/article/india/rahul-gandhi-jibe-pm-modi-donald-trump-new-global-tariffs-10544096/",
      "urlToImage": "https://images.indianexpress.com/2026/02/rahul-gandhi-parliament-1-1.jpg",
      "publishedAt": "2026-02-21T08:05:15Z",
      "content": "Leader of Opposition in Lok Sabha Rahul Gandhi on Saturday made a jibe at Prime Minister Narendra Modi again over the trade deal between India and the United States, saying the latter would “surrende… [+2950 chars]"
    },
    {
      "source": {
        "id": null,
        "name": "The Indian Express"
      },
      "author": "Express Global Desk",
      "title": "Iranian students hold first large anti-government protests since deadly January crackdown",
      "description": "The protests come amid rising tensions between Iran and the United States over Tehran’s nuclear programme.",
      "url": "https://indianexpress.com/article/world/iranian-students-hold-first-large-anti-government-protest-10545124/",
      "urlToImage": "https://images.indianexpress.com/2026/02/US-2-19.jpg",
      "publishedAt": "2026-02-21T23:50:45Z",
      "content": "Students at several universities across Iran have staged anti-government protests, marking the first demonstrations on this scale since last months deadly crackdown, according to the BBC.Hundreds of … [+2710 chars]"
    },
    {
      "source": {
        "id": null,
        "name": "The New Republic"
      },
      "author": "Jason Linkins",
      "title": "There’s Only One Way to Eradicate Trumpism for Good",
      "description": "One of the weirder journalistic spectacles of the Trump era has been watching mainstream news organizations parachute into the hinterlands to try to understand the voters who ushered in, and continue to support, this age of cruelty in America. A recent classi…",
      "url": "https://newrepublic.com/post/206818/accountability-crime-eradicate-trumpism-democrats",
      "urlToImage": "https://images.newrepublic.com/fc53fd87a7be7ca3b6305d3c0aef65f60664ad86.jpeg?w=1200&h=630&crop=faces&fit=crop&fm=jpg",
      "publishedAt": "2026-02-21T11:00:00Z",
      "content": "Bombs over Latin America: Its giving Wag the Dog, if you ask me. The administration, seemingly hot to bring back neoconservative military conquest, soft-launched its latest regime change war in Venez… [+2463 chars]"
    },
    {
      "source": {
        "id": null,
        "name": "Floodlightnews.org"
      },
      "author": "Evan Simon, Floodlight",
      "title": "‘A different set of rules’: Thermal drone footage shows Musk’s AI power plant flouting clean air regulations",
      "description": "Images confirm xAI is continuing to defy EPA regulations in Mississippi to power its flagship data centers.",
      "url": "https://floodlightnews.org/thermal-drone-footage-musk-ai-plant-epa-rules/",
      "urlToImage": "https://grist.org/wp-content/uploads/2026/02/SouthavenThermalSplitScreen_SIMON.jpg?quality=75&strip=all",
      "publishedAt": "2026-02-21T14:00:00Z",
      "content": "This story was originally published by Floodlight, a nonprofit newsroom that investigates the powers stalling climate action, and produced in partnership with The Guardian.\r\nElon Musks artificial int… [+8919 chars]"
    },
    {
      "source": {
        "id": "cbc-news",
        "name": "CBC News"
      },
      "author": null,
      "title": "What's next for Trump's tariffs after Supreme Court ruling",
      "description": "Based simply on the barely suppressed anger that U.S. President Donald Trump showed throughout his news conference on the Supreme Court's decision on tariffs, it's a fair bet that Friday was the worst day so far of his second term.",
      "url": "https://www.cbc.ca/news/world/trump-tariffs-supreme-court-analysis-9.7099838",
      "urlToImage": "https://i.cbc.ca/ais/f1304151-795c-4c11-bb0d-fb01cb40e342,1771617550458/full/max/0/default.jpg?im=Crop%2Crect%3D%28411%2C180%2C3332%2C1874%29%3BResize%3D620",
      "publishedAt": "2026-02-21T09:00:00Z",
      "content": "Based on the visibly simmering anger that U.S. President Donald Trump barely managed to suppress throughout his news conference on the Supreme Court's tariff decision, it's a fair bet that Friday was… [+6041 chars]"
    },
    {
      "source": {
        "id": "cbc-news",
        "name": "CBC News"
      },
      "author": null,
      "title": "What to know about the Gordie Howe Windsor-Detroit bridge at the centre of Donald Trump's threats",
      "description": "U.S. Democrats are probing the relationship between Donald Trump and the owner of the nearly century-old Ambassador Bridge linking Detroit and Windsor, Ont., after the president threatened to block this year's planned opening of a competing crossing — the Gor…",
      "url": "https://www.cbc.ca/news/canada/windsor/gordie-howe-bridge-backgrounder-9.7100029",
      "urlToImage": "https://i.cbc.ca/ais/1.7638158,1771622946953/full/max/0/default.jpg?im=Crop%2Crect%3D%280%2C222%2C4240%2C2385%29%3BResize%3D620",
      "publishedAt": "2026-02-21T09:00:00Z",
      "content": "U.S. Democrats are probing the relationship between President Donald Trump and the owner of the Ambassador Bridge linking Detroit and Windsor, Ont., after the president threatened to block the openin… [+4909 chars]"
    },
    {
      "source": {
        "id": null,
        "name": "Slate Magazine"
      },
      "author": "Mary Ziegler",
      "title": "Texas Is Prosecuting a Midwife for Abortion. Its Case Is Already Falling Apart.",
      "description": "Even charges like the ones Rojas faces can be devastating, whether or not a jury ever convicts.",
      "url": "https://slate.com/news-and-politics/2026/02/texas-midwife-abortion-prosecution-ken-paxton-fail.html",
      "urlToImage": "https://compote.slate.com/images/8f925afa-cd59-423c-b1d3-3520e19b616f.jpeg?crop=1560%2C1040%2Cx0%2Cy0&width=1560",
      "publishedAt": "2026-02-21T14:00:00Z",
      "content": "Sign up for the Slatest to get the most insightful analysis, criticism, and advice out there, delivered to your inbox daily.\r\nSince the fall of abortion rights, no abortion provider has been convicte… [+7129 chars]"
    },
    {
      "source": {
        "id": null,
        "name": "TheBlaze"
      },
      "author": "Carlos Garcia",
      "title": "Praise rolls in for high school suspending hundreds of students over anti-ICE walkout: 'Adults are taking charge'",
      "description": "A high school in Virginia suspended over 300 students for walking out of class for an anti-Immigration and Customs Enforcement protest, and many on social media have applauded the action.On February 13, students at Woodbridge High School marched off of campus…",
      "url": "https://www.theblaze.com/news/praise-rolls-in-for-high-school-suspending-hundreds-of-students-over-anti-ice-walkout-adults-are-taking-charge",
      "urlToImage": "https://www.theblaze.com/media-library/praise-rolls-in-for-high-school-suspending-hundreds-of-students-over-anti-ice-walkout-adults-are-taking-charge.jpg?id=64968061&width=1200&height=600&coordinates=0%2C166%2C0%2C167",
      "publishedAt": "2026-02-21T13:00:00Z",
      "content": "A high school in Virginia suspended over 300 students for walking out of class for an anti-Immigration and Customs Enforcement protest, and many on social media have applauded the action.\r\nOn Februar… [+2260 chars]"
    },
    {
      "source": {
        "id": null,
        "name": "Twistedsifter.com"
      },
      "author": "Kyra Piperides",
      "title": "East Antarctica Is Incredibly Cold, But It Has Lost 1.85 Trillion Tons Of Ice In The Past Two Decades Due To Global Warming",
      "description": "You might be chilly right now, but that doesn't mean the world is getting colder.",
      "url": "http://twistedsifter.com/2026/02/the-us-is-cold-east-antarctica-is-colder-but-dont-mistake-this-for-a-world-that-isnt-getting-net-warmer-every-decade/",
      "urlToImage": "https://twistedsifter.com/wp-content/uploads/2026/01/Penguin.jpg",
      "publishedAt": "2026-02-21T20:48:32Z",
      "content": "Pexels\r\nIf you’re in any of the continents experiencing a particularly harsh winter right now, you’ll likely be crossing your fingers and hoping that the cold spell will be over soon.\r\nAnd with tempe… [+2553 chars]"
    },
    {
      "source": {
        "id": null,
        "name": "CoinDesk"
      },
      "author": "Francisco Rodrigues",
      "title": "Bitcoin price slips after Trump hikes worldwide tariff to 15% from 10% despite Supreme Court decision",
      "description": "U.S. President Donald Trump announced a 15% worldwide tariff on imported goods, despite an earlier Supreme Court decision that invalidated earlier trade actions.",
      "url": "https://www.coindesk.com/markets/2026/02/21/bitcoin-price-slips-after-trump-hikes-worldwide-tariff-to-15-from-10-despite-supreme-court-decision",
      "urlToImage": "https://cdn.sanity.io/images/s3y3vcno/production/7e39720d9b7db4c55e718d03eb94c80c60a0861c-1920x1080.jpg?auto=format&w=960&h=540&crop=focalpoint&fit=clip&q=75&fm=jpg",
      "publishedAt": "2026-02-21T16:43:00Z",
      "content": "The price of bitcoin BTC\r\n$68,415.92 fell slightly on Saturday after U.S. President Donald Trump announced an additional increase to global tariffs, despite a U.S. Supreme Court decision that invalid… [+1016 chars]"
    },
    {
      "source": {
        "id": null,
        "name": "Consequence.net"
      },
      "author": "Chris Coplan",
      "title": "Kennedy Center Ice Rink Allegedly Vandalized by “Toxic Chemical”",
      "description": "Kennedy Center interim president Richard Grenell blamed the incident on \"Democrats.\"\nKennedy Center Ice Rink Allegedly Vandalized by “Toxic Chemical”\nChris Coplan",
      "url": "https://consequence.net/2026/02/trump-kennedy-chemical-attack/",
      "urlToImage": "https://consequence.net/wp-content/uploads/2026/02/toxic-chemicaltrump-kennedy-center-x1.jpg",
      "publishedAt": "2026-02-21T18:34:40Z",
      "content": "The Kennedy Center’s outdoor ice rink was the target of what officials described as a “calculated, malicious attack.”\r\nThe alleged incident took place early Friday morning (February 20th) when a “tox… [+1694 chars]"
    },
    {
      "source": {
        "id": null,
        "name": "Yahoo Entertainment"
      },
      "author": "Jeff Lewis",
      "title": "Goldman Sachs Lowers its Price Target on Snowflake Inc. (SNOW) to $246 but Maintains a Buy Rating",
      "description": "Snowflake Inc. (NYSE:SNOW) is among the 10 Best Consensus Buy-Rated Stocks to Invest in. On February 11, 2026, Goldman Sachs lowered its price target on...",
      "url": "https://finance.yahoo.com/news/goldman-sachs-lowers-price-target-153933486.html",
      "urlToImage": "https://s.yimg.com/os/en/insidermonkey.com/7f9ef0ed464138faad1e79d4686d9f99",
      "publishedAt": "2026-02-21T15:39:33Z",
      "content": "Snowflake Inc. (NYSE:SNOW) is among the 10 Best Consensus Buy-Rated Stocks to Invest in. On February 11, 2026, Goldman Sachs lowered its price target on Snowflake Inc. (NYSE:SNOW) to $246 from $286 p… [+1910 chars]"
    },
    {
      "source": {
        "id": null,
        "name": "Yahoo Entertainment"
      },
      "author": "Vardah Gill",
      "title": "Morgan Stanley Raises Welltower (WELL) Price Target on Strong Growth Outlook",
      "description": "Welltower Inc. (NYSE:WELL) is included among the 14 Best Real Estate Stocks to Buy According to Hedge Funds. On February 18, Morgan Stanley raised its price ...",
      "url": "https://finance.yahoo.com/news/morgan-stanley-raises-welltower-well-141206404.html",
      "urlToImage": "https://s.yimg.com/ny/api/res/1.2/9izkb4F0CqqfrSCtDz0bEQ--/YXBwaWQ9aGlnaGxhbmRlcjt3PTEyMDA7aD02NzM-/https://media.zenfs.com/en/insidermonkey.com/2d27859b117aba0cd428df2224895dea",
      "publishedAt": "2026-02-21T14:12:06Z",
      "content": "Welltower Inc. (NYSE:WELL) is included among the 14 Best Real Estate Stocks to Buy According to Hedge Funds.\r\nMorgan Stanley Raises Welltower (WELL) Price Target on Strong Growth Outlook\r\nOn February… [+2538 chars]"
    },
    {
      "source": {
        "id": null,
        "name": "Yahoo Entertainment"
      },
      "author": "Angelica Ballesteros",
      "title": "First Majestic (AG) Skyrockets by Double-Digits on 22% PT Hike",
      "description": "We recently published 10 Stocks Outrunning the Market; 3 on a High. First Majestic Silver Corp. (NYSE:AG) was one of the best performers on Friday. First...",
      "url": "https://finance.yahoo.com/news/first-majestic-ag-skyrockets-double-161425841.html",
      "urlToImage": "https://s.yimg.com/os/en/insidermonkey.com/0b039d8987d1d0e2cc26f01f11cf038f",
      "publishedAt": "2026-02-21T16:14:25Z",
      "content": "We recently published 10 Stocks Outrunning the Market; 3 on a High. First Majestic Silver Corp. (NYSE:AG) was one of the best performers on Friday.\r\nFirst Majestic rallied for a third consecutive day… [+2117 chars]"
    },
    {
      "source": {
        "id": null,
        "name": "Yahoo Entertainment"
      },
      "author": "Angelica Ballesteros",
      "title": "B2Gold (BTG) Climbs 5.27% on Return to Profitability",
      "description": "We recently published 10 Stocks Outrunning the Market; 3 on a High. B2Gold Corp. (NYSEAmerican:BTG) was one of the best performers on Friday. B2Gold jumped...",
      "url": "https://finance.yahoo.com/news/b2gold-btg-climbs-5-27-161252632.html",
      "urlToImage": "https://s.yimg.com/ny/api/res/1.2/rfW3kUdg_ahQd3X0LDVpnQ--/YXBwaWQ9aGlnaGxhbmRlcjt3PTEyMDA7aD05MDA-/https://media.zenfs.com/en/insidermonkey.com/60f1ec14409dec5a1b21c86ad006d2ad",
      "publishedAt": "2026-02-21T16:12:52Z",
      "content": "We recently published 10 Stocks Outrunning the Market; 3 on a High. B2Gold Corp. (NYSEAmerican:BTG) was one of the best performers on Friday.\r\nB2Gold jumped by 5.27 percent on Friday to close at $5.3… [+1928 chars]"
    },
    {
      "source": {
        "id": null,
        "name": "Yahoo Entertainment"
      },
      "author": "Jeff Lewis",
      "title": "Truist Increases its Price Target on AECOM (ACM) to $132 and Maintains a Buy Rating",
      "description": "AECOM (NYSE:ACM) is among the 10 Best Consensus Buy-Rated Stocks to Invest in. On February 11, 2026, Truist analyst Jamie Cook increased the firm’s price...",
      "url": "https://finance.yahoo.com/news/truist-increases-price-target-aecom-153923497.html",
      "urlToImage": "https://s.yimg.com/os/en/insidermonkey.com/478222ee52df2fefc775ed27c42c9df4",
      "publishedAt": "2026-02-21T15:39:23Z",
      "content": "AECOM (NYSE:ACM) is among the 10 Best Consensus Buy-Rated Stocks to Invest in. On February 11, 2026, Truist analyst Jamie Cook increased the firms price target on AECOM (NYSE:ACM) to $132 from $126 a… [+2030 chars]"
    },
    {
      "source": {
        "id": null,
        "name": "Yahoo Entertainment"
      },
      "author": "Jeff Lewis",
      "title": "RBC Capital Lowers its Price Target on Autodesk, Inc. (ADSK) to $340 and Maintains an Outperform Rating",
      "description": "Autodesk, Inc. (NASDAQ:ADSK) is among the 10 Best Consensus Buy-Rated Stocks to Invest in. On February 11, 2026, RBC Capital analyst Matthew Hedberg lowered ...",
      "url": "https://finance.yahoo.com/news/rbc-capital-lowers-price-target-153950473.html",
      "urlToImage": "https://s.yimg.com/os/en/insidermonkey.com/36c6360c65e42618f8609126645d6c2f",
      "publishedAt": "2026-02-21T15:39:50Z",
      "content": "Autodesk, Inc. (NASDAQ:ADSK) is among the 10 Best Consensus Buy-Rated Stocks to Invest in. On February 11, 2026, RBC Capital analyst Matthew Hedberg lowered the firms price target on Autodesk, Inc. (… [+2224 chars]"
    },
    {
      "source": {
        "id": null,
        "name": "Yahoo Entertainment"
      },
      "author": "Vardah Gill",
      "title": "Cushman & Wakefield (CWK) Delivers Record Revenue as Commercial Real Estate Demand Holds Firm",
      "description": "Cushman & Wakefield Limited (NYSE:CWK) is included among the 14 Best Real Estate Stocks to Buy According to Hedge Funds. Cushman & Wakefield Limited...",
      "url": "https://finance.yahoo.com/news/cushman-wakefield-cwk-delivers-record-134319753.html",
      "urlToImage": "https://s.yimg.com/ny/api/res/1.2/FfyYKZb.aga8.rqko0qKdw--/YXBwaWQ9aGlnaGxhbmRlcjt3PTEyMDA7aD02NzM-/https://media.zenfs.com/en/insidermonkey.com/a94338b6e964732cf2dce2e4d6c98429",
      "publishedAt": "2026-02-21T13:43:19Z",
      "content": "Cushman &amp; Wakefield Limited (NYSE:CWK) is included among the 14 Best Real Estate Stocks to Buy According to Hedge Funds.\r\nCushman &amp; Wakefield (CWK) Delivers Record Revenue as Commercial Real … [+2408 chars]"
    },
    {
      "source": {
        "id": null,
        "name": "Yahoo Entertainment"
      },
      "author": "Vardah Gill",
      "title": "Citi Trims Mid-America Apartment Communities (MAA) Target Amid Multifamily Sector Uncertainty",
      "description": "Mid-America Apartment Communities, Inc. (NYSE:MAA) is included among the 14 Best Real Estate Stocks to Buy According to Hedge Funds. Top 100 Places Where the...",
      "url": "https://finance.yahoo.com/news/citi-trims-mid-america-apartment-135839583.html",
      "urlToImage": "https://s.yimg.com/ny/api/res/1.2/fGOL.Pa64RtAtnqpga6JZg--/YXBwaWQ9aGlnaGxhbmRlcjt3PTEyMDA7aD02NzM-/https://media.zenfs.com/en/insidermonkey.com/446ffb0aff04206598cab104d22fbca1",
      "publishedAt": "2026-02-21T13:58:39Z",
      "content": "Mid-America Apartment Communities, Inc. (NYSE:MAA) is included among the 14 Best Real Estate Stocks to Buy According to Hedge Funds.\r\nCiti Trims Mid-America Apartment Communities (MAA) Target Amid Mu… [+2683 chars]"
    },
    {
      "source": {
        "id": null,
        "name": "Yahoo Entertainment"
      },
      "author": "Vardah Gill",
      "title": "Extra Space Storage (EXR) Price Target Cut as Wells Fargo Flags Sector Caution",
      "description": "Extra Space Storage Inc. (NYSE:EXR) is included among the 14 Best Real Estate Stocks to Buy According to Hedge Funds. On February 5, Wells Fargo lowered its ...",
      "url": "https://finance.yahoo.com/news/extra-space-storage-exr-price-135607371.html",
      "urlToImage": "https://s.yimg.com/ny/api/res/1.2/VTKbs9DrkinEeeeS.usB5A--/YXBwaWQ9aGlnaGxhbmRlcjt3PTEyMDA7aD02NzM-/https://media.zenfs.com/en/insidermonkey.com/93f46ae533364147fadb0a4251ca6389",
      "publishedAt": "2026-02-21T13:56:07Z",
      "content": "Extra Space Storage Inc. (NYSE:EXR) is included among the 14 Best Real Estate Stocks to Buy According to Hedge Funds.\r\nExtra Space Storage (EXR) Price Target Cut as Wells Fargo Flags Sector Caution\r\n… [+2679 chars]"
    },
    {
      "source": {
        "id": null,
        "name": "Yahoo Entertainment"
      },
      "author": "Angelica Ballesteros",
      "title": "Pinterest (PINS) Surges 5.96% on Bargain-Hunting as Firm Falls to Record Low",
      "description": "We recently published 10 Stocks Outrunning the Market; 3 on a High. Pinterest Inc. (NYSE:PINS) was one of the best performers on Friday. Pinterest saw its...",
      "url": "https://finance.yahoo.com/news/pinterest-pins-surges-5-96-161303750.html",
      "urlToImage": "https://s.yimg.com/os/en/insidermonkey.com/4d13883589d820e13ca157d46db96ea1",
      "publishedAt": "2026-02-21T16:13:03Z",
      "content": "We recently published 10 Stocks Outrunning the Market; 3 on a High. Pinterest Inc. (NYSE:PINS) was one of the best performers on Friday.\r\nPinterest saw its share prices jump by 5.96 percent on Friday… [+1914 chars]"
    },
    {
      "source": {
        "id": null,
        "name": "Yahoo Entertainment"
      },
      "author": "Parshwa Turakhiya",
      "title": "'Word-Salad Nonsense'—Fed President Kashkari Says Crypto Advocates Can't Explain The Use Case",
      "description": "Minneapolis Fed President Neel Kashkari on Thursday attacked crypto and stablecoins, saying proponents deliver “word-salad nonsense answers” when pressed to ...",
      "url": "https://finance.yahoo.com/news/word-salad-nonsense-fed-president-223109736.html",
      "urlToImage": "https://s.yimg.com/os/en/benzinga_79/36742349b175ba7b755fb1b5e179acec",
      "publishedAt": "2026-02-21T22:31:09Z",
      "content": "Benzinga and Yahoo Finance LLC may earn commission or revenue on some items through the links below.\r\nMinneapolis Fed President Neel Kashkari on Thursday attacked crypto and stablecoins, saying propo… [+12206 chars]"
    },
    {
      "source": {
        "id": null,
        "name": "Snopes.com"
      },
      "author": "Taija PerryCook",
      "title": "Did Jesse Jackson once praise Trump for his commitment to underserved communities?",
      "description": "In January 1999, Civil Rights leader Jesse Jackson praised Donald Trump, saying the future U.S. president embraced the \"underserved communities.\"",
      "url": "https://www.snopes.com//fact-check/jesse-jackson-once-praised-trump/",
      "urlToImage": "https://mediaproxy.snopes.com/width/1200/https://media.snopes.com/2026/02/jesse_jackson_and_trump_in_1988.png",
      "publishedAt": "2026-02-21T00:06:00Z",
      "content": "Claim:\r\nIn January 1999, Civil Rights leader Jesse Jackson praised Donald Trump, saying the future U.S. president embraced the \"underserved communities.\"\r\nIn 1999, as future U.S. President Donald Tru… [+5095 chars]"
    },
    {
      "source": {
        "id": null,
        "name": "Crooksandliars.com"
      },
      "author": "Chris capper Liebenthal",
      "title": "Union Membership Hits Sixteen Year High Because Of Trump",
      "description": "from The Guardian reports that union membership in the United States climbed by about 500,000, bringing the total to 16.5 million people. That is the highest it's been since 2009.\nThe increase is due largely to the Trump regime attacking workers' rights, most…",
      "url": "https://crooksandliars.com/2026/02/union-membership-hits-sixteen-year-high",
      "urlToImage": "https://crooksandliars.com/files/primary_image/26/02/screenshot_2026-02-19_153753.png",
      "publishedAt": "2026-02-21T19:09:15Z",
      "content": "from The Guardian reports that union membership in the United States climbed by about 500,000, bringing the total to 16.5 million people. That is the highest it's been since 2009.\r\nThe increase is du… [+699 chars]"
    },
    {
      "source": {
        "id": null,
        "name": "Crooksandliars.com"
      },
      "author": "Ed Scarce",
      "title": "'Fuck Trump, Vote Juliana' Ad Goes Up In Illinois",
      "description": "An interesting Democratic primary in Illinois next month, pitting current Lt. Governor Juliana Stratton against Reps. Raja Krishnamoorthi and Robin Kelly. Krishnamoorthi had been expected to win comfortably, as he'd raised an obscene amount of money (nearing …",
      "url": "https://crooksandliars.com/2026/02/fuck-trump-vote-juliana-ad-goes-illinois",
      "urlToImage": "https://crooksandliars.com/files/primary_image/26/02/ctc-l-stratton-tv-commercial-005-ezgif.com-webp-to-jpg-converter.jpg",
      "publishedAt": "2026-02-21T02:17:13Z",
      "content": "An interesting Democratic primary in Illinois next month, pitting current Lt. Governor Juliana Stratton against Reps. Raja Krishnamoorthi and Robin Kelly. Krishnamoorthi had been expected to win comf… [+1280 chars]"
    },
    {
      "source": {
        "id": null,
        "name": "Crooksandliars.com"
      },
      "author": "John Amato",
      "title": "Fox News Host: I Thought We Were Done With War In Middle East",
      "description": "Maybe for the first time, Fox News host Rachel Campos-Duffy spoke out against an action Trump may take in any way.\n\nFox and Friends opened their program by discussing the possibility that Trump will call for an attack on Iran.\nRachel Campos-Duffy opened by sa…",
      "url": "https://crooksandliars.com/2026/02/fox-news-host-i-thought-we-were-done-war",
      "urlToImage": "https://crooksandliars.com/files/mediaposters/2026/02/58591.jpg",
      "publishedAt": "2026-02-21T19:08:50Z",
      "content": "Maybe for the first time, Fox News host Rachel Campos-Duffy spoke out against an action Trump may take in any way.Fox and Friends opened their program by discussing the possibility that Trump will ca… [+2668 chars]"
    },
    {
      "source": {
        "id": null,
        "name": "Crooksandliars.com"
      },
      "author": "John Amato",
      "title": "What's On Trump's Face?",
      "description": "During a speech in Rome, Georgia, on Thursday, Trump's new orange dye job was so caustic that it reflected light in a way that made his face look like a weird mirror.\nBright, shiny face, Trump.\nThis is a new look. \nOpen thread.\nread more",
      "url": "https://crooksandliars.com/2026/02/whats-trumps-face",
      "urlToImage": "https://crooksandliars.com/files/primary_image/26/02/vlcsnap-2026-02-20-08h35m55s562.png",
      "publishedAt": "2026-02-21T04:00:01Z",
      "content": "During a speech in Rome, Georgia, on Thursday, Trump's new orange dye job was so caustic that it reflected light in a way that made his face look like a weird mirror.\r\nBright, shiny face, Trump.\r\nThi… [+30 chars]"
    },
    {
      "source": {
        "id": null,
        "name": "Crooksandliars.com"
      },
      "author": "Red Painter",
      "title": "Mitch McConnell's Sweet Revenge: He's Blocking SAVE Act",
      "description": "Donald Trump is having an extra bad Friday. First, the Supreme Court struck down Trump's tariffs. Then came horrible economic news. Now we hear that Mitch McConnell is intentionally blocking the SAVE America Act, a legislation that Republicans really want to …",
      "url": "https://crooksandliars.com/2026/02/mitch-mcconnell-gets-his-revenge",
      "urlToImage": "https://crooksandliars.com/files/primary_image/26/02/trump_3.jpg",
      "publishedAt": "2026-02-21T13:59:01Z",
      "content": "Donald Trump is having an extra bad Friday. First, the Supreme Court struck down Trump's tariffs. Then came horrible economic news. Now we hear that Mitch McConnell is intentionally blocking the SAVE… [+1857 chars]"
    },
    {
      "source": {
        "id": null,
        "name": "Crooksandliars.com"
      },
      "author": "Chris capper Liebenthal",
      "title": "Top Wisconsin Republican Announces He's Quitting",
      "description": "On Thursday, Wisconsin Speaker of the Assembly Robin Vos announced that he would not be running for reelection. \nVos claimed that he had had a heart attack in November, which prompted him to decide not to run again due to the stress of the job. It should be n…",
      "url": "https://crooksandliars.com/2026/02/top-wisconsin-republican-announces-hes",
      "urlToImage": "https://crooksandliars.com/files/primary_image/26/02/robin_vos_-_pr_watch.jpg",
      "publishedAt": "2026-02-21T14:38:00Z",
      "content": "On Thursday, Wisconsin Speaker of the Assembly Robin Vos announced that he would not be running for reelection. \r\nVos claimed that he had had a heart attack in November, which prompted him to decide … [+1431 chars]"
    },
    {
      "source": {
        "id": null,
        "name": "Crooksandliars.com"
      },
      "author": "Heather",
      "title": "Fox Host: GOP 'Silently, Quietly Breathing A Sigh Of Relief' On Tariff Ruling",
      "description": "Fox's Shannon Bream discusses what Republicans are telling them behind closed doors on these illegal Trump tariffs. They all know they're a tax on Americans and inflation and the economy is going to hurt them in the midterm elections, but apparently, the cowa…",
      "url": "https://crooksandliars.com/2026/02/foxs-bream-gop-silently-quietly-breathing",
      "urlToImage": "https://crooksandliars.com/files/primary_image/26/02/fox-bream-tariffs-022026.png",
      "publishedAt": "2026-02-21T13:58:43Z",
      "content": "Fox's Shannon Bream discusses what Republicans are telling them behind closed doors on these illegal Trump tariffs. They all know they're a tax on Americans and inflation and the economy is going to … [+2144 chars]"
    },
    {
      "source": {
        "id": null,
        "name": "Crooksandliars.com"
      },
      "author": "John Amato",
      "title": "RFK Jr Is A Sick Man",
      "description": "Trump's anti-vaccine, anti-scientific research HHS Secretary spends more time doing push-ups, wearing jeans in ice-baths, and making videos with washed up rock singers than keeping the country healthy.\nThe Telegraph writes,\"The 72-year-old, who has declared t…",
      "url": "https://crooksandliars.com/2026/02/rfk-jr-sick-man",
      "urlToImage": "https://crooksandliars.com/files/primary_image/26/02/rfk-bath-jeans_0.jpg",
      "publishedAt": "2026-02-21T13:59:16Z",
      "content": "Trump's anti-vaccine, anti-scientific research HHS Secretary spends more time doing push-ups, wearing jeans in ice-baths, and making videos with washed up rock singers than keeping the country health… [+1025 chars]"
    },
    {
      "source": {
        "id": null,
        "name": "CleanTechnica"
      },
      "author": "Press Release",
      "title": "Sierra Club Statement on Trump Administration Opening Millions of Acres of Protected Public Lands to Mining",
      "description": "WASHINGTON, D.C. — The Department of the Interior announced today it would revoke two public land orders to open more than two million acres of public lands in Alaska to drilling and mining. In an announcement late Friday afternoon, Interior Secretary Doug Bu…",
      "url": "https://cleantechnica.com/2026/02/20/sierra-club-statement-on-trump-administration-opening-millions-of-acres-of-protected-public-lands-to-mining/",
      "urlToImage": "https://cleantechnica.com/wp-content/uploads/2023/05/Malaspina-Feature-Photo.jpg",
      "publishedAt": "2026-02-21T02:16:36Z",
      "content": "Support CleanTechnica's work through a Substack subscription or on Stripe. \r\nOr support our Kickstarter campaign!\r\nWASHINGTON, D.C. The Department of the Interior announced today it would revoke two … [+2387 chars]"
    },
    {
      "source": {
        "id": null,
        "name": "CleanTechnica"
      },
      "author": "Tina Casey",
      "title": "Cultural Architects, Trojan Horses, And Another EV Startup To Challenge Tesla",
      "description": "The US startup 1854 Motors aims to be the first domestic automaker to introduce sodium-ion batteries in a full sized EV, beginning with the Pierce pickup truck.\nThe post Cultural Architects, Trojan Horses, And Another EV Startup To Challenge Tesla appeared fi…",
      "url": "https://cleantechnica.com/2026/02/21/cultural-architects-trojan-horses-and-another-ev-startup-to-challenge-tesla/",
      "urlToImage": "https://cleantechnica.com/wp-content/uploads/2026/02/Screenshot-2026-02-20-at-8.46.00-PM.png",
      "publishedAt": "2026-02-21T14:52:15Z",
      "content": "Support CleanTechnica's work through a Substack subscription or on Stripe. \r\nOr support our Kickstarter campaign!\r\nAn EV startup that centers on early adopters and ethical consumerism sure sounds lik… [+8889 chars]"
    },
    {
      "source": {
        "id": "new-york-magazine",
        "name": "New York Magazine"
      },
      "author": "Ed Kilgore",
      "title": "How Justice Alito’s Retirement Might Upend the Midterms",
      "description": "Justice Samuel Alito’s retirement might upend the midterms. Republicans believe the Kavanaugh fight saved the GOP Senate in 2018. They’d love to see a repeat, but it could backfire this time.",
      "url": "http://nymag.com/intelligencer/article/alito-retirement-might-upend-the-midterms.html",
      "urlToImage": "https://pyxis.nymag.com/v1/imgs/712/68f/c34a86c6841c9801212c5e55f5fb495b8c-alito-age.1x.rsocial.w1200.jpg",
      "publishedAt": "2026-02-21T10:00:27Z",
      "content": "This week, theres been a lot of attention focused on the U.S. Supreme Court, thanks to its stunning decision blowing up the rationale for Donald Trumps tariff agenda. In his bitter remarks about the … [+7388 chars]"
    },
    {
      "source": {
        "id": "new-york-magazine",
        "name": "New York Magazine"
      },
      "author": "John Herrman",
      "title": "X Really Is Pulling Users to the Right",
      "description": "Two recent bodies of research indicate that X really is pulling its users to the right, and elites may not be as immune to this kind of algorithmic radicalization as they think.",
      "url": "http://nymag.com/intelligencer/article/x-really-is-pulling-users-to-the-right.html",
      "urlToImage": "https://pyxis.nymag.com/v1/imgs/130/392/9dcbdf4063fc72707eb27ec0b87b3fa052-musktrump-screentime.1x.rsocial.w1200.jpg",
      "publishedAt": "2026-02-21T12:00:00Z",
      "content": "After buying Twitter, Elon Musk rebuilt it to his own specifications and preferences. This resulted in an environment we may gently call friendlier to the discussion and promotion of right-wing polit… [+5982 chars]"
    },
    {
      "source": {
        "id": null,
        "name": "TheStranger.com"
      },
      "author": "Julianne Bell",
      "title": "Our Favorite Bowls of Hot Soup in Seattle",
      "description": "Don’t worry, we’ll start yelling at politicians again soon.\n \n by Julianne Bell\n \n \n \n It’s cold. Earlier this week we saw a few tiny flurries of snow, even! And while some weather reports suggest we might soon break out of this chilly, mid-40s prison we’ve b…",
      "url": "https://www.thestranger.com/food-and-drink/2026/02/20/80486858/our-favorite-bowls-of-hot-soup-in-seattle",
      "urlToImage": "https://media2.fdncms.com/stranger/imager/u/large/80486871/isarn_thai_soul_kitchen_brooke_fitts014.webp",
      "publishedAt": "2026-02-21T00:20:00Z",
      "content": "Its cold. Earlier this week we saw a few tiny flurries of snow, even! And while some weather reports suggest we might soon break out of this chilly, mid-40s prison weve been locked in, itll be by jus… [+9042 chars]"
    },
    {
      "source": {
        "id": null,
        "name": "Dazed"
      },
      "author": "Elliot Hoste",
      "title": "Nightlife icon David Hoyle talks Heated Rivalry and cruising in Mugler",
      "description": "In this Dazed exclusive premiere, the Mancunian performance artist and French maison drop the latest episode in their new digital series",
      "url": "https://www.dazeddigital.com/fashion/article/69692/1/mugler-the-divine-david-hoyle-heated-rivalry-miguel-castro-freitas?utm_source=Link&utm_medium=Link&utm_campaign=RSSFeed&utm_term=nightlife-icon-david-hoyle-talks-heated-rivalry-and-cruising-in-mugler",
      "urlToImage": "https://images-prod.dazeddigital.com/1032/48-317-1032-688/azure/dazed-prod/1430/8/1438134.jpg",
      "publishedAt": "2026-02-21T12:56:00Z",
      "content": "In the late 1990s, when he was just a teenager, Muglers creative director Miguel Castro Freitas became obsessed with the Mancunian performance artist David Hoyle. Back then Hoyle was known as the Div… [+9229 chars]"
    }
  ]
}